pyrqbit-0.1.0.dist-info/METADATA
pyrqbit-0.1.0.dist-info/WHEEL
pyrqbit-0.1.0.dist-info/licenses/LICENSE
pyrqbit.libs/libcrypto-ef58def3.so.3
pyrqbit.libs/libssl-660a6abe.so.3
pyrqbit/__init__.py
pyrqbit/__init__.pyi
pyrqbit/client.py
pyrqbit/pyrqbit.abi3.so
pyrqbit-0.1.0.dist-info/RECORD
