Metadata-Version: 2.4
Name: pyrqbit
Version: 0.1.0
Classifier: Development Status :: 3 - Alpha
Classifier: Intended Audience :: Developers
Classifier: License :: OSI Approved :: Apache Software License
Classifier: Programming Language :: Python :: 3
Classifier: Programming Language :: Python :: 3.8
Classifier: Programming Language :: Python :: 3.9
Classifier: Programming Language :: Python :: 3.10
Classifier: Programming Language :: Python :: 3.11
Classifier: Programming Language :: Python :: 3.12
Classifier: Programming Language :: Rust
License-File: LICENSE
Summary: Python bindings for librqbit - a feature-rich BitTorrent client library
Keywords: bittorrent,torrent,p2p
License: Apache-2.0
Requires-Python: >=3.10
Project-URL: Homepage, https://github.com/fakerybakery/pyrqbit
Project-URL: Repository, https://github.com/fakerybakery/pyrqbit
Project-URL: Documentation, https://github.com/fakerybakery/pyrqbit#readme
